setup.cfg
setup.py
sql2gee/__init__.py
sql2gee/sql2gee.py
sql2gee.egg-info/PKG-INFO
sql2gee.egg-info/SOURCES.txt
sql2gee.egg-info/dependency_links.txt
sql2gee.egg-info/not-zip-safe
sql2gee.egg-info/requires.txt
sql2gee.egg-info/top_level.txt