Metadata-Version: 1.1
Name: sql2gee
Version: 0.1.2
Summary: Library to convert SQL-like queries into Google Earth Engine syntax, and return the responses
Home-page: https://github.com/Vizzuality/sql2gee
Author: Benjamin Laken
Author-email: benjamin.laken@vizzuality.com
License: MIT
Download-URL: https://github.com/Vizzuality/sql2gee/tarball/0.1.2
Keywords: EarthEngine,SQL
Platform: UNKNOWN
